tw2.jqplugins.lightbox-2.11.3-py3.7-nspkg.pth
tw2/jqplugins/lightbox/__init__.py
tw2/jqplugins/lightbox/static/css/lightbox.css
tw2/jqplugins/lightbox/static/css/lightbox.min.css
tw2/jqplugins/lightbox/static/images/close.png
tw2/jqplugins/lightbox/static/images/loading.gif
tw2/jqplugins/lightbox/static/images/next.png
tw2/jqplugins/lightbox/static/images/prev.png
tw2/jqplugins/lightbox/static/js/lightbox.js
tw2/jqplugins/lightbox/static/js/lightbox.min.js
tw2/jqplugins/lightbox/static/js/lightbox.min.map
tw2.jqplugins.lightbox-2.11.3.dist-info/METADATA
tw2.jqplugins.lightbox-2.11.3.dist-info/WHEEL
tw2.jqplugins.lightbox-2.11.3.dist-info/entry_points.txt
tw2.jqplugins.lightbox-2.11.3.dist-info/namespace_packages.txt
tw2.jqplugins.lightbox-2.11.3.dist-info/top_level.txt
tw2.jqplugins.lightbox-2.11.3.dist-info/RECORD
